django_get_autologin-0.2.dist-info/DESCRIPTION.rst
django_get_autologin-0.2.dist-info/METADATA
django_get_autologin-0.2.dist-info/RECORD
django_get_autologin-0.2.dist-info/WHEEL
django_get_autologin-0.2.dist-info/metadata.json
django_get_autologin-0.2.dist-info/top_level.txt
get_autologin/__init__.py
get_autologin/admin.py
get_autologin/apps.py
get_autologin/backends.py
get_autologin/models.py
get_autologin/tests.py
get_autologin/urls.py
get_autologin/views.py
get_autologin/migrations/0001_initial.py
get_autologin/migrations/__init__.py
